LICENSE
MANIFEST.in
README.md
pyproject.toml
setup.py
src/msglc/__init__.py
src/msglc/config.py
src/msglc/index.py
src/msglc/reader.py
src/msglc/toc.py
src/msglc/unpacker.py
src/msglc/utility.py
src/msglc/writer.py
src/msglc.egg-info/PKG-INFO
src/msglc.egg-info/SOURCES.txt
src/msglc.egg-info/dependency_links.txt
src/msglc.egg-info/requires.txt
src/msglc.egg-info/top_level.txt