Metadata-Version: 2.4
Name: msglc
Version: 251227
Summary: msgpack with lazy/partial loading containers
Author-email: Theodore Chang <tlcfem@gmail.com>
Maintainer-email: Theodore Chang <tlcfem@gmail.com>
License-Expression: GPL-3.0-or-later
Project-URL: Homepage, https://github.com/TLCFEM/msglc
Project-URL: Bug Reports, https://github.com/TLCFEM/msglc/issuess
Project-URL: Source, https://github.com/TLCFEM/msglc
Keywords: msgpack,serialization,lazy loading
Classifier: Development Status :: 5 - Production/Stable
Classifier: Intended Audience :: Developers
Classifier: Topic :: File Formats :: JSON
Classifier: Programming Language :: Python :: 3
Classifier: Programming Language :: Python :: 3.9
Classifier: Programming Language :: Python :: 3.10
Classifier: Programming Language :: Python :: 3.11
Classifier: Programming Language :: Python :: 3.12
Classifier: Programming Language :: Python :: 3.13
Classifier: Programming Language :: Python :: 3.14
Classifier: Programming Language :: Python :: 3 :: Only
Requires-Python: >=3.9
License-File: LICENSE
Requires-Dist: msgpack>=1
Requires-Dist: bitarray
Requires-Dist: fsspec>=2021.9.0
Provides-Extra: dev
Requires-Dist: pytest-cov; extra == "dev"
Requires-Dist: pytest-benchmark; extra == "dev"
Requires-Dist: pytest-asyncio; extra == "dev"
Requires-Dist: ruff; extra == "dev"
Requires-Dist: mike; extra == "dev"
Requires-Dist: mkdocs-material; extra == "dev"
Requires-Dist: mkdocs-awesome-pages-plugin; extra == "dev"
Requires-Dist: mkdocstrings[python]; extra == "dev"
Provides-Extra: numpy
Requires-Dist: numpy; extra == "numpy"
Provides-Extra: msgspec
Requires-Dist: msgspec; extra == "msgspec"
Provides-Extra: ormsgpack
Requires-Dist: ormsgpack; extra == "ormsgpack"
Provides-Extra: s3fs
Requires-Dist: s3fs; extra == "s3fs"
Provides-Extra: pyarrow
Requires-Dist: pyarrow; extra == "pyarrow"
Dynamic: license-file
